code2flownew7/__init__.py
code2flownew7/engine.py
code2flownew7/javascript.py
code2flownew7/model.py
code2flownew7/php.py
code2flownew7/python.py
code2flownew7/ruby.py
code2flownew7-2.5.0.dist-info/LICENSE
code2flownew7-2.5.0.dist-info/METADATA
code2flownew7-2.5.0.dist-info/WHEEL
code2flownew7-2.5.0.dist-info/entry_points.txt
code2flownew7-2.5.0.dist-info/top_level.txt
code2flownew7-2.5.0.dist-info/RECORD
