Metadata-Version: 2.1
Name: code2flownew7
Version: 2.5.0
Summary: Visualize your source code as DOT flowcharts
Home-page: https://github.com/AhmedSalihCezayir/code2flow
Author: Scott Rogowski
Author-email: scottmrogowski@gmail.com
License: MIT
Download-URL: https://github.com/AhmedSalihCezayir/code2flow/archive/code2flow-2.5.0.tar.gz
Platform: UNKNOWN
Classifier: Natural Language :: English
Classifier: Programming Language :: Python :: 3
Classifier: License :: OSI Approved :: MIT License
Classifier: Operating System :: OS Independent
Requires-Python: >=3.6
License-File: LICENSE
